{
  "last_updated": "2026-07-21 19:14:39",
  "debuts": [
    {
      "event_name": "Water Festival 2026",
      "event_date": "August 18th - August 24th 2026",
      "new_pokemon": [
        "Cramorant",
        "Arrokuda",
        "Barraskewda"
      ],
      "new_shiny": [],
      "pokemon_images": {
        "Cramorant": "https://www.serebii.net/pokemongo/pokemon/845.png",
        "Arrokuda": "https://www.serebii.net/pokemongo/pokemon/846.png",
        "Barraskewda": "https://www.serebii.net/pokemongo/pokemon/847.png"
      },
      "event_type": "global"
    },
    {
      "event_name": "Summer Marathon Arctic Embers",
      "event_date": "August 4th - August 10th 2026",
      "new_pokemon": [],
      "new_shiny": [
        "Snom",
        "Frosmoth"
      ],
      "pokemon_images": {
        "Snom": "https://www.serebii.net/pokemongo/pokemon/shiny/872.png",
        "Frosmoth": "https://www.serebii.net/pokemongo/pokemon/shiny/873.png"
      },
      "event_type": "global"
    },
    {
      "event_name": "Ultra Unlock 10th Anniversary Edition",
      "event_date": "July 21st - July 27th 2026",
      "new_pokemon": [
        "Pikachu (Professor Willow's Assistant)"
      ],
      "new_shiny": [],
      "pokemon_images": {
        "Pikachu (Professor Willow's Assistant)": "https://www.serebii.net/pokemongo/pokemon/025-willow.png"
      },
      "event_type": "global"
    },
    {
      "event_name": "Willow's Birthday Research",
      "event_date": "July 21st 2026",
      "new_pokemon": [
        "Pikachu (Professor Willow's Assistant)"
      ],
      "new_shiny": [],
      "pokemon_images": {
        "Pikachu (Professor Willow's Assistant)": "https://www.serebii.net/pokemongo/pokemon/025-willow.png"
      },
      "event_type": "global"
    }
  ]
}